website_worth/__init__.py
website_worth/calcs.py
website_worth/cli.py
website_worth/constants.py
website_worth-0.0.2.dist-info/METADATA
website_worth-0.0.2.dist-info/WHEEL
website_worth-0.0.2.dist-info/entry_points.txt
website_worth-0.0.2.dist-info/top_level.txt
website_worth-0.0.2.dist-info/RECORD
