Metadata-Version: 2.1
Name: website-worth
Version: 0.0.2
Summary: Worth of websites calculator
Home-page: https://github.com/maledorak/website-worth
Author: Mariusz Korzekwa
Author-email: maledorak@gmail.com
License: MIT license
Keywords: website_worth
Platform: UNKNOWN
Classifier: Development Status :: 2 - Pre-Alpha
Classifier: Intended Audience :: Developers
Classifier: License :: OSI Approved :: MIT License
Classifier: Natural Language :: English
Classifier: Programming Language :: Python :: 3
Classifier: Programming Language :: Python :: 3.5
Classifier: Programming Language :: Python :: 3.6
Classifier: Programming Language :: Python :: 3.7
Requires-Python: >=3.5
Requires-Dist: Click (>=7.0)
Requires-Dist: requests (>=2.22)
Requires-Dist: beautifulsoup4 (>=4.8)
Requires-Dist: fake-useragent (>=0.1.11)
